csci355/lab7/src/6.3-mealy.v
module FSM (
  input wire clk,
  input wire reset,
  input wire w,
  output reg z
);
  parameter q0 = 1'b0, q1 = 1'b1;

  reg[1:0] current_state, next_state;

  always @(posedge clk or posedge reset) begin
    case(current_state)
      q0: begin
        if(w) begin
          z = 1'b0;
          next_state = q1;
        end else begin
          z = 1'b0;
          next_state = q0;
        end
      end
      q1: begin
        if(w) begin
          z = 1'b1;
          next_state = q1;
        end else begin
          z = 1'b0;
          next_state = q0;
        end
      end
      
      default: begin 
        z = 1'b0;
        next_state = q0;
      end
    endcase

    if(reset) begin
      current_state = q0;
      next_state = q0;
    end
    else 
      current_state = next_state;
  end
endmodule

csci355/lab7/testbench/6.3-mealy_tb.v
`timescale 1ns/1ns
`include "6.3-mealy.v"

module mealy63_tb();
  reg clk, reset, w;
  wire z;

  FSM f(clk, reset, w, z);

  always #5 clk = ~clk;

  initial begin
    $dumpfile("mealy63_tb.vcd");
    $dumpvars(0, mealy63_tb);
    
    clk = 0;
    reset = 1;
    w = 0;

    #10; reset = 0;

    #10; w = 0;
    #10; w = 1;
    #10; w = 0;
    #10; w = 1;
    #10; w = 1;
    #10; w = 1;
    #10; w = 0;
    #10; w = 1;
    #10; w = 0;
    #10; w = 1;
    #10; w = 0;
    #10; w = 0;
    #10; w = 1;
    #10; w = 0;
    #10; w = 1;
    #10; w = 1;
    #10; w = 0;
    #10; w = 0;

    $finish;
    $display("Test complete");
  end
endmodule

csci355/lab7/build/mealy63_tb.vcd
$date
	Tue Nov 26 16:06:27 2024
$end
$version
	Icarus Verilog
$end
$timescale
	1ns
$end
$scope module mealy63_tb $end
$var wire 1 ! z $end
$var reg 1 " clk $end
$var reg 1 # reset $end
$var reg 1 $ w $end
$scope module f $end
$var wire 1 " clk $end
$var wire 1 # reset $end
$var wire 1 $ w $end
$var parameter 1 % q0 $end
$var parameter 1 & q1 $end
$var reg 2 ' current_state [1:0] $end
$var reg 2 ( next_state [1:0] $end
$var reg 1 ! z $end
$upscope $end
$upscope $end
$enddefinitions $end
$comment Show the parameter values. $end
$dumpall
1&
0%
$end
#0
$dumpvars
b0 (
b0 '
0$
1#
0"
0!
$end
#5
1"
#10
0"
0#
#15
1"
#20
0"
#25
1"
#30
0"
1$
#35
b1 '
b1 (
1"
#40
0"
0$
#45
b0 '
b0 (
1"
#50
0"
1$
#55
b1 '
b1 (
1"
#60
0"
#65
1!
1"
#70
0"
#75
1"
#80
0"
0$
#85
b0 '
b0 (
0!
1"
#90
0"
1$
#95
b1 '
b1 (
1"
#100
0"
0$
#105
b0 '
b0 (
1"
#110
0"
1$
#115
b1 '
b1 (
1"
#120
0"
0$
#125
b0 '
b0 (
1"
#130
0"
#135
1"
#140
0"
1$
#145
b1 '
b1 (
1"
#150
0"
0$
#155
b0 '
b0 (
1"
#160
0"
1$
#165
b1 '
b1 (
1"
#170
0"
#175
1!
1"
#180
0"
0$
#185
b0 '
b0 (
0!
1"
