csci355/lab7/src/6.4-mealy.v
module FSM (
  input wire clk,
  input wire reset,
  input wire w,
  output reg z
);
  parameter q0 = 2'b00, q1 = 2'b01, q2 = 2'b10, q3 = 2'b11;

  reg[1:0] current_state, next_state;

  always @(posedge clk or posedge reset) begin
    case(current_state)
      q0: begin
        if(w) begin
          z = 1'b0;
          next_state = q1;
        end else begin
          z = 1'b0;
          next_state = q0;
        end
      end
      q1: begin
        if(w) begin
          z = 1'b0;
          next_state = q3;
        end else begin
          z = 1'b0;
          next_state = q2;
        end
      end
      q2: begin
        if(w) begin
          z = 1'b1;
          next_state = q1;
        end else begin
          z = 1'b0;
          next_state = q0;
        end
      end
      q3: begin
        if(w) begin
          z = 1'b0;
          next_state = q3;
        end else begin
          z = 1'b1;
          next_state = q2;
        end
      end
      
      default: begin 
        z = 1'b0;
        next_state = q0;
      end
    endcase

    if(reset) begin
      current_state = q0;
      next_state = q0;
    end
    else 
      current_state = next_state;
  end
endmodule

csci355/lab7/testbench/6.4-mealy_tb.v
`timescale 1ns/1ns
`include "6.4-mealy.v"

module mealy64_tb();
  reg clk, reset, w;
  wire z;

  FSM f(clk, reset, w, z);

  always #5 clk = ~clk;

  initial begin
    $dumpfile("mealy64_tb.vcd");
    $dumpvars(0, mealy64_tb);
    
    clk = 0;
    reset = 1;
    w = 0;

    #10; reset = 0;

    #10; w = 0;
    #10; w = 1;
    #10; w = 0;
    #10; w = 1;
    #10; w = 1;
    #10; w = 1;
    #10; w = 0;
    #10; w = 1;
    #10; w = 0;
    #10; w = 1;
    #10; w = 0;
    #10; w = 0;
    #10; w = 1;
    #10; w = 0;
    #10; w = 1;
    #10; w = 1;
    #10; w = 0;
    #10; w = 0;

    $finish;
    $display("Test complete");
  end
endmodule

csci355/lab7/build/mealy64_tb.vcd
$date
	Tue Nov 26 16:06:32 2024
$end
$version
	Icarus Verilog
$end
$timescale
	1ns
$end
$scope module mealy64_tb $end
$var wire 1 ! z $end
$var reg 1 " clk $end
$var reg 1 # reset $end
$var reg 1 $ w $end
$scope module f $end
$var wire 1 " clk $end
$var wire 1 # reset $end
$var wire 1 $ w $end
$var parameter 2 % q0 $end
$var parameter 2 & q1 $end
$var parameter 2 ' q2 $end
$var parameter 2 ( q3 $end
$var reg 2 ) current_state [1:0] $end
$var reg 2 * next_state [1:0] $end
$var reg 1 ! z $end
$upscope $end
$upscope $end
$enddefinitions $end
$comment Show the parameter values. $end
$dumpall
b11 (
b10 '
b1 &
b0 %
$end
#0
$dumpvars
b0 *
b0 )
0$
1#
0"
0!
$end
#5
1"
#10
0"
0#
#15
1"
#20
0"
#25
1"
#30
0"
1$
#35
b1 )
b1 *
1"
#40
0"
0$
#45
b10 )
b10 *
1"
#50
0"
1$
#55
b1 )
b1 *
1!
1"
#60
0"
#65
b11 )
b11 *
0!
1"
#70
0"
#75
1"
#80
0"
0$
#85
b10 )
b10 *
1!
1"
#90
0"
1$
#95
b1 )
b1 *
1"
#100
0"
0$
#105
b10 )
b10 *
0!
1"
#110
0"
1$
#115
b1 )
b1 *
1!
1"
#120
0"
0$
#125
b10 )
b10 *
0!
1"
#130
0"
#135
b0 )
b0 *
1"
#140
0"
1$
#145
b1 )
b1 *
1"
#150
0"
0$
#155
b10 )
b10 *
1"
#160
0"
1$
#165
b1 )
b1 *
1!
1"
#170
0"
#175
b11 )
b11 *
0!
1"
#180
0"
0$
#185
b10 )
b10 *
1!
1"
