csci355/lab7/src/6.2-moore.v
module FSM (
  input wire clk,
  input wire reset,
  input wire w,
  output reg z
);
  parameter q0 = 3'b000, q1 = 3'b001, q2 = 3'b010, q3 = 3'b011, q4 = 3'b100, q5 = 3'b101;

  reg[2:0] current_state, next_state;

  always @(posedge clk or posedge reset) begin
    if(reset) begin
      current_state = q0;
      next_state = q0;
    end
    else 
      current_state = next_state;

    case(current_state)
      q0: begin
        z = 1'b0;
        if(w)
          next_state = q1;
        else
          next_state = q0;
      end
      q1: begin
        z = 1'b0;
        if(w)
          next_state = q3;
        else
          next_state = q2;
      end
      q2: begin
        z = 1'b0;
        if(w)
          next_state = q5;
        else
          next_state = q0;
      end
      q3: begin
        z = 1'b0;
        if(w)
          next_state = q3;
        else
          next_state = q4;
      end
      q4: begin
        z = 1'b1;
        if(w)
          next_state = q5;
        else
          next_state = q0;
      end
      q5: begin
        z = 1'b1;
        if(w)
          next_state = q3;
        else
          next_state = q2;
      end
      default: begin
        z = 1'b0;
        next_state = q0;
      end
    endcase
  end

endmodule

csci355/lab7/testbench/6.2-moore_tb.v
`timescale 1ns/1ns
`include "6.2-moore.v"

module moore62_tb();
  reg clk, reset, w;
  wire z;

  FSM f(clk, reset, w, z);

  always #5 clk = ~clk;

  initial begin
    $dumpfile("moore62_tb.vcd");
    $dumpvars(0, moore62_tb);
    
    clk = 0;
    reset = 1;
    w = 0;

    #10; reset = 0;

    #10; w = 0;
    #10; w = 1;
    #10; w = 0;
    #10; w = 1;
    #10; w = 1;
    #10; w = 1;
    #10; w = 0;
    #10; w = 1;
    #10; w = 0;
    #10; w = 1;
    #10; w = 0;
    #10; w = 0;
    #10; w = 1;
    #10; w = 0;
    #10; w = 1;
    #10; w = 1;
    #10; w = 0;
    #10; w = 0;
    #10; w = 0;

    #10; w = 0;
    #10; w = 1;
    #10; w = 0;
    #10; w = 1;
    #10; w = 0;
    #10; w = 1;
    #10; w = 0;
    #10; w = 1;
    #10; w = 0;
    #10;

    $finish;
    $display("Test complete");
  end
endmodule

csci355/lab7/build/moore62_tb.vcd
$date
	Tue Nov 26 16:56:57 2024
$end
$version
	Icarus Verilog
$end
$timescale
	1ns
$end
$scope module moore62_tb $end
$var wire 1 ! z $end
$var reg 1 " clk $end
$var reg 1 # reset $end
$var reg 1 $ w $end
$scope module f $end
$var wire 1 " clk $end
$var wire 1 # reset $end
$var wire 1 $ w $end
$var parameter 3 % q0 $end
$var parameter 3 & q1 $end
$var parameter 3 ' q2 $end
$var parameter 3 ( q3 $end
$var parameter 3 ) q4 $end
$var parameter 3 * q5 $end
$var reg 3 + current_state [2:0] $end
$var reg 3 , next_state [2:0] $end
$var reg 1 ! z $end
$upscope $end
$upscope $end
$enddefinitions $end
$comment Show the parameter values. $end
$dumpall
b101 *
b100 )
b11 (
b10 '
b1 &
b0 %
$end
#0
$dumpvars
b0 ,
b0 +
0$
1#
0"
0!
$end
#5
1"
#10
0"
0#
#15
1"
#20
0"
#25
1"
#30
0"
1$
#35
b1 ,
1"
#40
0"
0$
#45
b10 ,
b1 +
1"
#50
0"
1$
#55
b101 ,
b10 +
1"
#60
0"
#65
b11 ,
1!
b101 +
1"
#70
0"
#75
0!
b11 +
1"
#80
0"
0$
#85
b100 ,
1"
#90
0"
1$
#95
b101 ,
1!
b100 +
1"
#100
0"
0$
#105
b10 ,
b101 +
1"
#110
0"
1$
#115
b101 ,
0!
b10 +
1"
#120
0"
0$
#125
b10 ,
1!
b101 +
1"
#130
0"
#135
b0 ,
0!
b10 +
1"
#140
0"
1$
#145
b1 ,
b0 +
1"
#150
0"
0$
#155
b10 ,
b1 +
1"
#160
0"
1$
#165
b101 ,
b10 +
1"
#170
0"
#175
b11 ,
1!
b101 +
1"
#180
0"
0$
#185
b100 ,
0!
b11 +
1"
#190
0"
#195
b0 ,
1!
b100 +
1"
#200
0"
#205
0!
b0 +
1"
#210
0"
#215
1"
#220
0"
1$
#225
b1 ,
1"
#230
0"
0$
#235
b10 ,
b1 +
1"
#240
0"
1$
#245
b101 ,
b10 +
1"
#250
0"
0$
#255
b10 ,
1!
b101 +
1"
#260
0"
1$
#265
b101 ,
0!
b10 +
1"
#270
0"
0$
#275
b10 ,
1!
b101 +
1"
#280
0"
1$
#285
b101 ,
0!
b10 +
1"
#290
0"
0$
#295
b10 ,
1!
b101 +
1"
