csci355/lab5/src/full-adder.v
// Structural Specification
module fulladder (
  input wire ci, xi, yi,
  output wire so, co
);
  and(a1, xi, yi);
  xor(a2, xi, yi);

  and(b1, a2, ci);
  
  xor(so, a2, ci);
  or(co, a1, b1);
endmodule

csci355/lab5/testbench/full-adder_tb.v
`timescale 1ns/1ns
`include "full-adder.v"

module fulladder_tb ();
  reg ci, x, y;
  wire f, co;

  fulladder ut(ci, x, y, f, co);

  initial begin
    $dumpfile("fulladder_tb.vcd");
    $dumpvars(0, fulladder_tb);

    ci = 0;
    x = 0;
    y = 0;
      #20;
    ci = 1;
    x = 0;
    y = 0;
      #20;
    ci = 0;
    x = 1;
    y = 0;
      #20;
    ci = 1;
    x = 1;
    y = 0;
      #20;
    ci = 0;
    x = 0;
    y = 1;
      #20;
    ci = 1;
    x = 0;
    y = 1;
      #20;
    ci = 0;
    x = 1;
    y = 1;
      #20;
    ci = 1;
    x = 1;
    y = 1;
      #20;
      
  $display("Test complete");
  end

endmodule

csci355/lab5/build/fulladder_tb.vcd
$date
	Fri Nov  1 20:02:19 2024
$end
$version
	Icarus Verilog
$end
$timescale
	1ns
$end
$scope module fulladder_tb $end
$var wire 1 ! f $end
$var wire 1 " co $end
$var reg 1 # ci $end
$var reg 1 $ x $end
$var reg 1 % y $end
$scope module ut $end
$var wire 1 & a1 $end
$var wire 1 ' a2 $end
$var wire 1 ( b1 $end
$var wire 1 # ci $end
$var wire 1 " co $end
$var wire 1 ! so $end
$var wire 1 $ xi $end
$var wire 1 % yi $end
$upscope $end
$upscope $end
$enddefinitions $end
$comment Show the parameter values. $end
$dumpall
$end
#0
$dumpvars
0(
0'
0&
0%
0$
0#
0"
0!
$end
#20
1!
1#
#40
1'
1!
1$
0#
#60
1"
1(
0!
1#
#80
0"
0(
1!
1%
0$
0#
#100
1"
1(
0!
1#
#120
1&
0'
0(
0!
1$
0#
#140
1!
1#
